{
  "project_info": {
    "project_number": "626065256298",
    "project_id": "inkquesttattoo-f88ac",
    "storage_bucket": "inkquesttattoo-f88ac.firebasestorage.app"
  },
  "client": [
    {
      "client_info": {
        "mobilesdk_app_id": "1:626065256298:android:d470ad960a187377e2ff13",
        "android_client_info": {
          "package_name": "com.inkquest.tattoo"
        }
      },
      "oauth_client": [],
      "api_key": [
        {
          "current_key": "AIzaSyDYCquDA6UwA_XkG1NE7DY6zuxpQDkL4gM"
        }
      ],
      "services": {
        "appinvite_service": {
          "other_platform_oauth_client": []
        }
      }
    }
  ],
  "configuration_version": "1"
}